{
  "name": "bed",
  "description": "Small BDD testing framework for D.",
  "copyright": "Copyright © 2014, Pedro Tacla Yamada",
  "license": "MIT",
  "authors": [
    "Pedro Tacla Yamada"
  ],
  "dependencies": {
    "ncurses": "~master",
    "colorize": ">=1.0.1",
    "pyjamas": "~master"
  },
  "configurations": [
    {
      "name": "bed",
      "sourcePaths": [
        "source"
      ]
    },
    {
      "name": "unittest",
      "targetType": "executable",
      "sourcePaths": [
        "source",
        "tests"
      ],
      "buildOptions": [
        "unittests"
      ],
      "dflags": [
        "-main"
      ]
    }
  ]
}
